kink/__init__.py
kink/__verstion__.py
kink/container.py
kink/errors/__init__.py
kink/errors/conainer_error.py
kink/errors/execution_error.py
kink/errors/resolver_error.py
kink/errors/service_error.py
kink/inject.py
kink/py.typed
kink/typing_support.py
kink-0.8.1.dist-info/LICENSE
kink-0.8.1.dist-info/METADATA
kink-0.8.1.dist-info/WHEEL
kink-0.8.1.dist-info/RECORD
