Metadata-Version: 2.1
Name: kink
Version: 0.8.1
Summary: Dependency injection for python.
Home-page: https://github.com/kodemore/kink
License: MIT
Keywords: kink,dependency injection
Author: Dawid Kraczkowski
Author-email: dawid.kraczkowski@gmail.com
Requires-Python: >=3.8,<4.0
Classifier: License :: OSI Approved :: MIT License
Classifier: Programming Language :: Python :: 3
Classifier: Programming Language :: Python :: 3.8
Classifier: Programming Language :: Python :: 3.9
Classifier: Programming Language :: Python :: 3.10
Classifier: Programming Language :: Python :: 3.11
Classifier: Topic :: Software Development :: Libraries
Classifier: Topic :: Software Development :: Libraries :: Python Modules
Requires-Dist: typing_extensions (>=4.9.0,<5.0.0)
Project-URL: Documentation, https://github.com/kodemore/kink
Project-URL: Repository, https://github.com/kodemore/kink
